dafni_cli/__init__.py
dafni_cli/login.py
dafni_cli/nims.py
dafni_cli/urls.py
dafni_cli_dafni_facility-0.0.9.dist-info/LICENSE
dafni_cli_dafni_facility-0.0.9.dist-info/METADATA
dafni_cli_dafni_facility-0.0.9.dist-info/WHEEL
dafni_cli_dafni_facility-0.0.9.dist-info/top_level.txt
dafni_cli_dafni_facility-0.0.9.dist-info/RECORD
